{
  "attributes": [],
  "isd_as": "18-ffaa:1:34",
  "dispatched_ports": "31000-32767",
  "mtu": 1472,
  "control_service": {
    "cs": {
      "addr": "127.0.0.1:31000"
    }
  },
  "discovery_service": {
    "cs": {
      "addr": "127.0.0.1:31000"
    }
  },
  "border_routers": {
    "br": {
      "internal_addr": "127.0.0.1:31002",
      "interfaces": {
        "1": {
          "underlay": {
            "local": "10.100.0.34:51114",
            "remote": "10.100.0.31:51114"
          },
          "isd_as": "18-ffaa:1:31",
          "link_to": "parent",
          "mtu": 1472
        },
        "2": {
          "underlay": {
            "local": "10.100.0.34:51314",
            "remote": "10.100.0.33:51314"
          },
          "isd_as": "18-ffaa:1:33",
          "link_to": "parent",
          "mtu": 1472
        }
      }
    }
  }
}